ads/__init__.py
ads/base.py
ads/config.py
ads/exceptions.py
ads/export.py
ads/libraries.py
ads/metrics.py
ads/sandbox.py
ads/search.py
ads/utils.py
ads/tests/__init__.py
ads/tests/mocks.py
ads/tests/test_base.py
ads/tests/test_export.py
ads/tests/test_metrics.py
ads/tests/test_sandbox.py
ads/tests/test_search.py
ads/tests/test_utils.py
ads/tests/stubdata/__init__.py
ads/tests/stubdata/export.py
ads/tests/stubdata/metrics.py
ads/tests/stubdata/solr.py
ads-0.12.6.dist-info/LICENSE
ads-0.12.6.dist-info/METADATA
ads-0.12.6.dist-info/WHEEL
ads-0.12.6.dist-info/top_level.txt
ads-0.12.6.dist-info/RECORD
