Metadata-Version: 2.1
Name: ads
Version: 0.12.6
Summary: A Python module for NASA's ADS that doesn't suck.
Home-page: http://www.github.com/andycasey/ads/
Author: Andrew R. Casey
Author-email: andy@astrowizici.st
License: MIT
License-File: LICENSE
Requires-Dist: six
Requires-Dist: requests
Requires-Dist: werkzeug
Requires-Dist: mock
Provides-Extra: tests
Requires-Dist: httpretty>=0.8.10; extra == "tests"
